perfwhiz/__init__.py
perfwhiz/credentials.py
perfwhiz/mkcdict_perf_script.py
perfwhiz/mkcdict_plugin.py
perfwhiz/perf_formatter.py
perfwhiz/perfcap.py
perfwhiz/perfmap.py
perfwhiz/perfmap_common.py
perfwhiz/perfmap_core.py
perfwhiz/perfmap_kvm_exit_types.py
perfwhiz/perfmap_sw_kvm_exits.py
perfwhiz/umsgpack.py
perfwhiz/perfmap_charts.jinja
perfwhiz/perfmap_heatmaps.jinja
perfwhiz-0.3.1.dist-info/top_level.txt
perfwhiz-0.3.1.dist-info/entry_points.txt
perfwhiz-0.3.1.dist-info/pbr.json
perfwhiz-0.3.1.dist-info/METADATA
perfwhiz-0.3.1.dist-info/DESCRIPTION.rst
perfwhiz-0.3.1.dist-info/metadata.json
perfwhiz-0.3.1.dist-info/WHEEL
perfwhiz-0.3.1.dist-info/RECORD
