Metadata-Version: 2.0
Name: perfwhiz
Version: 0.3.1
Summary: Tools for Linux perf
Home-page: https://github.com/cisco-oss-eng/perfwhiz
Author: Alec Hothan
Author-email: ahothan@cisco.com
License: UNKNOWN
Keywords: Linux perf tools
Platform: UNKNOWN
Classifier: Intended Audience :: Developers
Classifier: Intended Audience :: Information Technology
Classifier: Intended Audience :: System Administrators
Classifier: License :: OSI Approved :: Apache Software License
Classifier: Operating System :: POSIX :: Linux
Classifier: Operating System :: MacOS
Classifier: Programming Language :: Python
Classifier: Programming Language :: Python :: 2
Classifier: Programming Language :: Python :: 2.7
Requires-Dist: pbr (>=1.8)
Requires-Dist: msgpack-python (>=0.4.6)
Provides-Extra: analyzer
Requires-Dist: pandas (>=0.17); extra == 'analyzer'
Requires-Dist: numpy (>=1.10.1); extra == 'analyzer'
Requires-Dist: Jinja2 (>=2.8); extra == 'analyzer'
